atef/__init__.py
atef/__main__.py
atef/_version.py
atef/annotated_plans.py
atef/archive_device.py
atef/cache.py
atef/check.py
atef/config.py
atef/enums.py
atef/exceptions.py
atef/find_replace.py
atef/grafana.py
atef/ophyd_helpers.py
atef/plan_utils.py
atef/procedure.py
atef/pyepics_compat.py
atef/qt_helpers.py
atef/re_widgets.py
atef/reduce.py
atef/report.py
atef/result.py
atef/serialization.py
atef/tools.py
atef/type_hints.py
atef/util.py
atef/version.py
atef/walk.py
atef/yaml_support.py
atef/assets/SLAC_red.jpeg
atef/bin/__init__.py
atef/bin/check.py
atef/bin/check_main.py
atef/bin/config.py
atef/bin/config_main.py
atef/bin/main.py
atef/bin/scripts.py
atef/scripts/__init__.py
atef/scripts/converter_v0.py
atef/scripts/converter_v0_main.py
atef/scripts/pmgr_check.py
atef/scripts/pmgr_check_main.py
atef/tests/__init__.py
atef/tests/conftest.py
atef/tests/hxr_ebd_fee_checkout_helper.json
atef/tests/qt_utils.py
atef/tests/sample_plans.py
atef/tests/test_archived_device.py
atef/tests/test_commandline.py
atef/tests/test_comparison.py
atef/tests/test_comparison_device.py
atef/tests/test_comparison_tools.py
atef/tests/test_configuration.py
atef/tests/test_find_replace.py
atef/tests/test_grafana.py
atef/tests/test_helpers.py
atef/tests/test_ophyd.py
atef/tests/test_page.py
atef/tests/test_plan_utils.py
atef/tests/test_procedure.py
atef/tests/test_report.py
atef/tests/test_walk.py
atef/tests/test_widgets.py
atef/tests/configs/active_test.json
atef/tests/configs/all_fields.json
atef/tests/configs/blank_active.json
atef/tests/configs/blank_passive.json
atef/tests/configs/device_based.yml
atef/tests/configs/lfe.json
atef/tests/configs/ping_localhost.json
atef/tests/configs/pv_based.yml
atef/tests/profiles/user_group_permissions.yaml
atef/ui/action_row_run_widget.ui
atef/ui/action_row_widget.ui
atef/ui/add_row_widget.ui
atef/ui/any_comparison_widget.ui
atef/ui/any_value_widget.ui
atef/ui/archive_viewer_widget.ui
atef/ui/attr_comparison_row_widget.ui
atef-1.6.1.dist-info/licenses/AUTHORS.rst
atef-1.6.1.dist-info/licenses/LICENSE
atef-1.6.1.dist-info/METADATA
atef-1.6.1.dist-info/WHEEL
atef-1.6.1.dist-info/entry_points.txt
atef-1.6.1.dist-info/top_level.txt
atef-1.6.1.dist-info/RECORD
