Metadata-Version: 2.4
Name: atef
Version: 1.6.1
Summary: Python Automated Test Execution Framework
Author: SLAC National Accelerator Laboratory
License: Copyright (c) 2023, The Board of Trustees of the Leland Stanford Junior
Classifier: Development Status :: 2 - Pre-Alpha
Classifier: Natural Language :: English
Classifier: Programming Language :: Python :: 3
Requires-Python: >=3.9
License-File: LICENSE
License-File: AUTHORS.rst
Requires-Dist: apischema
Requires-Dist: archapp>=1.1.0
Requires-Dist: bluesky
Requires-Dist: bluesky-queueserver>=0.0.19
Requires-Dist: bluesky-widgets
Requires-Dist: databroker<2.0.0a0
Requires-Dist: happi
Requires-Dist: ipython
Requires-Dist: matplotlib<=3.9.0
Requires-Dist: numpy
Requires-Dist: ophyd
Requires-Dist: pcdsutils>=0.14.1
Requires-Dist: pydm
Requires-Dist: PyQt5
Requires-Dist: pyyaml
Requires-Dist: qtpy
Requires-Dist: reportlab
Requires-Dist: rich
Requires-Dist: typhos
Requires-Dist: typing-extensions
Provides-Extra: test
Requires-Dist: coverage; extra == "test"
Requires-Dist: flake8; extra == "test"
Requires-Dist: pytest; extra == "test"
Requires-Dist: pytest-timeout; extra == "test"
Requires-Dist: sphinx; extra == "test"
Requires-Dist: numpydoc; extra == "test"
Requires-Dist: sphinx-copybutton; extra == "test"
Requires-Dist: sphinx_rtd_theme; extra == "test"
Requires-Dist: doctr; extra == "test"
Requires-Dist: docs-versions-menu; extra == "test"
Requires-Dist: recommonmark; extra == "test"
Requires-Dist: pytest-asyncio; extra == "test"
Requires-Dist: pytest-qt; extra == "test"
Requires-Dist: pcdsdevices>=7.1.0; extra == "test"
Requires-Dist: sphinxcontrib-jquery; extra == "test"
Dynamic: license-file
